DAmon/__init__.py
DAmon/cli.py
DAmon/core.py
damon-0.1.2.dist-info/licenses/LICENSE
damon-0.1.2.dist-info/METADATA
damon-0.1.2.dist-info/WHEEL
damon-0.1.2.dist-info/entry_points.txt
damon-0.1.2.dist-info/top_level.txt
damon-0.1.2.dist-info/RECORD
