Metadata-Version: 2.4
Name: DAmon
Version: 0.1.2
Summary: A CLI tool to extract structured Q&A from documents using LLMs.
Home-page: https://github.com/simonliuyuwei/DataArragimon
Author: Simon Liu
Author-email: simonliuyuwei@gmail.com
Classifier: Programming Language :: Python :: 3
Classifier: License :: OSI Approved :: MIT License
Classifier: Operating System :: OS Independent
Classifier: Development Status :: 3 - Alpha
Classifier: Intended Audience :: Developers
Classifier: Topic :: Scientific/Engineering :: Artificial Intelligence
Classifier: Topic :: Text Processing
Requires-Python: >=3.8
License-File: LICENSE
Requires-Dist: Click<9.0,>=8.1.7
Requires-Dist: litellm<2.0,>=1.34.2
Requires-Dist: python-dotenv<2.0,>=1.0.1
Requires-Dist: PyPDF2<4.0,>=3.0.1
Requires-Dist: python-docx<2.0,>=1.1.0
Requires-Dist: python-pptx<1.0,>=0.6.23
Requires-Dist: pandas<3.0,>=2.2.2
Requires-Dist: loguru<1.0,>=0.7.2
Requires-Dist: tenacity<9.0,>=8.2.3
Requires-Dist: tqdm<5.0,>=4.66.4
Requires-Dist: openpyxl<4.0,>=3.1.2
Dynamic: author
Dynamic: author-email
Dynamic: classifier
Dynamic: description
Dynamic: description-content-type
Dynamic: home-page
Dynamic: license-file
Dynamic: requires-dist
Dynamic: requires-python
Dynamic: summary
